fast2common/__init__.py
fast2common/adb_controller.py
fast2common/ai_client.py
fast2common/animation_detector.py
fast2common/coordinate_converter.py
fast2common/element_locator.py
fast2common/exploration_strategy.py
fast2common/icon_locator.py
fast2common/screenshot_analyzer.py
fast2common/tab_manager.py
fast2common/text_locator.py
fast2common/ui_analyzer.py
fast2common/ui_assertions.py
fast2common/ui_change_detector.py
fast2common/ui_interaction.py
fast2common-0.4.0.dist-info/METADATA
fast2common-0.4.0.dist-info/WHEEL
fast2common-0.4.0.dist-info/top_level.txt
fast2common-0.4.0.dist-info/RECORD
