Metadata-Version: 2.4
Name: fast2common
Version: 0.4.0
Summary: Fast2 Common - Android automation testing and UI interaction toolkit
Author: Fast2 Team
License: MIT
Project-URL: Homepage, https://github.com/fast2/fast2common
Project-URL: Repository, https://github.com/fast2/fast2common
Project-URL: Issues, https://github.com/fast2/fast2common/issues
Keywords: android,automation,testing,ui,adb,mobile
Classifier: Development Status :: 4 - Beta
Classifier: Intended Audience :: Developers
Classifier: Topic :: Software Development :: Quality Assurance
Classifier: Topic :: Software Development :: Testing
Classifier: License :: OSI Approved :: MIT License
Classifier: Programming Language :: Python :: 3
Classifier: Programming Language :: Python :: 3.8
Classifier: Programming Language :: Python :: 3.9
Classifier: Programming Language :: Python :: 3.10
Classifier: Programming Language :: Python :: 3.11
Classifier: Programming Language :: Python :: 3.12
Classifier: Operating System :: OS Independent
Requires-Python: >=3.8
Requires-Dist: zhipuai>=1.0.0
Requires-Dist: Pillow>=9.0.0
Provides-Extra: dev
Requires-Dist: pytest>=7.0.0; extra == "dev"
Requires-Dist: pytest-cov>=3.0.0; extra == "dev"
Requires-Dist: black>=22.0.0; extra == "dev"
Requires-Dist: mypy>=0.950; extra == "dev"
Requires-Dist: flake8>=4.0.0; extra == "dev"
